llc/__init__.py
llc/ndimage.py
llc-0.2.0.dist-info/DESCRIPTION.rst
llc-0.2.0.dist-info/METADATA
llc-0.2.0.dist-info/RECORD
llc-0.2.0.dist-info/WHEEL
llc-0.2.0.dist-info/metadata.json
llc-0.2.0.dist-info/top_level.txt
