Metadata-Version: 2.0
Name: llc
Version: 0.2.0
Summary: Prettier LowLevelCallables
Home-page: https://github.com/jni/llc-tools
Author: Juan Nunez-Iglesias
Author-email: juan.n@unimelb.edu.au
License: BSD 3-clause
Platform: UNKNOWN
Classifier: Development Status :: 4 - Beta
Classifier: Environment :: Console
Classifier: Intended Audience :: Developers
Classifier: License :: OSI Approved :: BSD License
Classifier: Programming Language :: Python
Classifier: Programming Language :: Python :: 3
Classifier: Topic :: Scientific/Engineering
Classifier: Operating System :: Microsoft :: Windows
Classifier: Operating System :: POSIX
Classifier: Operating System :: Unix
Classifier: Operating System :: MacOS
